vtrim/__init__.py
vtrim/analyzer.py
vtrim/cli.py
vtrim/ffmpeg_utils.py
vtrim/model.py
vtrim/segment_utils.py
vtrim/xml_export.py
vtrim/yolov8n.pt
vtrim-0.1.4.dist-info/licenses/LICENSE
vtrim-0.1.4.dist-info/METADATA
vtrim-0.1.4.dist-info/WHEEL
vtrim-0.1.4.dist-info/entry_points.txt
vtrim-0.1.4.dist-info/top_level.txt
vtrim-0.1.4.dist-info/RECORD
