Metadata-Version: 2.4
Name: vtrim
Version: 0.1.4
Summary: Trim detects people in videos and trims segments—without re-encoding—preserving quality and speed.
Home-page: https://github.com/ai-libx/vtrim
Author: Chiawei Lee
Author-email: ljw@live.jp
License: Apache License v2
Classifier: Programming Language :: Python :: 3
Classifier: License :: OSI Approved :: Apache Software License
Classifier: Operating System :: OS Independent
Requires-Python: >=3.7
License-File: LICENSE
Dynamic: author
Dynamic: author-email
Dynamic: classifier
Dynamic: description
Dynamic: description-content-type
Dynamic: home-page
Dynamic: license
Dynamic: license-file
Dynamic: requires-python
Dynamic: summary
